Workbook
Name Anos: Planilha1!$C$35
Name Investimento_mensal: Planilha1!$C$34
Name Patrimonio_acumulado: Planilha1!$C$37
Name Progressão_investimento: Planilha1!$C$41
Name Rendimento_Carteira: Planilha1!$C$10
Name Salario: Planilha1!$C$9
Name Taxa_mensal: Planilha1!$C$36

Sheet Planilha1
B8: Configurações
B9: Salário | C9: 2500
B10: Rendimento Carteira | C10: 0.01
B11: Sugestão de investimento | C11: =Salario*30% -> 750
B13: PERFIL | C13: Agressivo
B14: VALOR ENVESTIDO NO MÊS: | C14: =C11 -> 750
B16: TIPO DE FII | C16: Percentual Sugerido | D16: Valores
B17: PAPEL | C17: =VLOOKUP($C$13&"-"&B17,Planilha2!$B$3:$E$21,4,FALSE) -> 0.5 | D17: =($C$14*VLOOKUP($C$13,Planilha2!$G$5:$I$8,2,FALSE))*Planilha1!C17 -> 187.5
B18: TIJOLO | C18: =VLOOKUP($C$13&"-"&B18,Planilha2!$B$3:$E$21,4,FALSE) -> 0.1 | D18: =($C$14*VLOOKUP($C$13,Planilha2!$G$5:$I$8,2,FALSE))*Planilha1!C18 -> 37.5
B19: HÍBRIDO | C19: =VLOOKUP($C$13&"-"&B19,Planilha2!$B$3:$E$21,4,FALSE) -> 0.05 | D19: =($C$14*VLOOKUP($C$13,Planilha2!$G$5:$I$8,2,FALSE))*Planilha1!C19 -> 18.75
B20: FOFs | C20: =VLOOKUP($C$13&"-"&B20,Planilha2!$B$3:$E$21,4,FALSE) -> 0.05 | D20: =($C$14*VLOOKUP($C$13,Planilha2!$G$5:$I$8,2,FALSE))*Planilha1!C20 -> 18.75
B21: DESENVOLVIMENTO | C21: =VLOOKUP($C$13&"-"&B21,Planilha2!$B$3:$E$21,4,FALSE) -> 0.2 | D21: =($C$14*VLOOKUP($C$13,Planilha2!$G$5:$I$8,2,FALSE))*Planilha1!C21 -> 75
B22: HOTELARIAS | C22: =VLOOKUP($C$13&"-"&B22,Planilha2!$B$3:$E$21,4,FALSE) -> 0.1 | D22: =($C$14*VLOOKUP($C$13,Planilha2!$G$5:$I$8,2,FALSE))*Planilha1!C22 -> 37.5
D23: =SUM(D17:D22) -> 375
A25: 2 | B25: TIPOS DE RENDA FIXA | C25: Percentual Sugerido | D25: Valores
A26: 5 | B26: Tesouro Direto | C26: =VLOOKUP($C$13&"-"&B26,Planilha2!$B$23:$E$38,4,FALSE) -> 0.15 | D26: =($C$14*VLOOKUP($C$13,Planilha2!$G$5:$I$8,3,FALSE))*C26 -> 56.25
A27: 10 | B27: CDB | C27: =VLOOKUP($C$13&"-"&B27,Planilha2!$B$23:$E$38,4,FALSE) -> 0.2 | D27: =($C$14*VLOOKUP($C$13,Planilha2!$G$5:$I$8,3,FALSE))*C27 -> 75
A28: 20 | B28: LCI e LCA | C28: =VLOOKUP($C$13&"-"&B28,Planilha2!$B$23:$E$38,4,FALSE) -> 0.15 | D28: =($C$14*VLOOKUP($C$13,Planilha2!$G$5:$I$8,3,FALSE))*C28 -> 56.25
A29: 30 | B29: CRI e CRA | C29: =VLOOKUP($C$13&"-"&B29,Planilha2!$B$23:$E$38,4,FALSE) -> 0.25 | D29: =($C$14*VLOOKUP($C$13,Planilha2!$G$5:$I$8,3,FALSE))*C29 -> 93.75
B30: Dedêntures | C30: =VLOOKUP($C$13&"-"&B30,Planilha2!$B$23:$E$38,4,FALSE) -> 0.25 | D30: =($C$14*VLOOKUP($C$13,Planilha2!$G$5:$I$8,3,FALSE))*C30 -> 93.75
D31: =SUM(D26:D30) -> 375
B33: INVESTIMENTO MENSAL
B34: Quanto investir por mês? | C34: =C11 -> 750
B35: Por quantos anos? | C35: 5
B36: Taxa de rendimento mensal? | C36: =Rendimento_Carteira -> 0.01
B37: Patrimônio acumulado durante o Tempo? | C37: =FV(Taxa_mensal,Anos*12,Investimento_mensal)*-1 -> 61252.252
B38: Dividendos Mensais ? | C38: =Patrimonio_acumulado*Rendimento_Carteira -> 612.52252
B40: PROGRESSÃO DOS INVESTIMENTOS | D40: Dividendo
B41: 2 anos | C41: =FV(Taxa_mensal,$A25*12,Investimento_mensal)*-1 -> 20230.099 | D41: =$C41*Rendimento_Carteira -> 202.30099
B42: 5 anos | C42: =FV(Taxa_mensal,$A26*12,Investimento_mensal)*-1 -> 61252.252 | D42: =$C42*Rendimento_Carteira -> 612.52252
B43: 10 anos | C43: =FV(Taxa_mensal,$A27*12,Investimento_mensal)*-1 -> 172529.02 | D43: =$C43*Rendimento_Carteira -> 1725.2902
B44: 20 anos | C44: =FV(Taxa_mensal,$A28*12,Investimento_mensal)*-1 -> 741941.52 | D44: =$C44*Rendimento_Carteira -> 7419.4152
B45: 30 anos | C45: =FV(Taxa_mensal,$A29*12,Investimento_mensal)*-1 -> 2621223.1 | D45: =$C45*Rendimento_Carteira -> 26212.231

Sheet Planilha2
B3: Chave | C3: PERFIL | D3: TIPO DE FII | E3: %
B4: =C4&"-"&D4 -> Conservador-PAPEL | C4: Conservador | D4: PAPEL | E4: 0.3
B5: =C5&"-"&D5 -> Conservador-TIJOLO | C5: Conservador | D5: TIJOLO | E5: 0.5 | G5: CHAVE | H5: FII | I5: Renda Fixa
B6: =C6&"-"&D6 -> Conservador-HÍBRIDO | C6: Conservador | D6: HÍBRIDO | E6: 0.1 | G6: Conservador | H6: 0.2 | I6: 0.8
B7: =C7&"-"&D7 -> Conservador-FOFs | C7: Conservador | D7: FOFs | E7: 0.1 | G7: Moderado | H7: 0.35 | I7: 0.65
B8: =C8&"-"&D8 -> Conservador-DESENVOLVIMENTO | C8: Conservador | D8: DESENVOLVIMENTO | E8: 0 | G8: Agressivo | H8: 0.5 | I8: 0.5
B9: =C9&"-"&D9 -> Conservador-HOTELARIAS | C9: Conservador | D9: HOTELARIAS | E9: 0
B10: =C10&"-"&D10 -> Moderado-PAPEL | C10: Moderado | D10: PAPEL | E10: 0.32
B11: =C11&"-"&D11 -> Moderado-TIJOLO | C11: Moderado | D11: TIJOLO | E11: 0.35
B12: =C12&"-"&D12 -> Moderado-HÍBRIDO | C12: Moderado | D12: HÍBRIDO | E12: 0.08
B13: =C13&"-"&D13 -> Moderado-FOFs | C13: Moderado | D13: FOFs | E13: 0.05
B14: =C14&"-"&D14 -> Moderado-DESENVOLVIMENTO | C14: Moderado | D14: DESENVOLVIMENTO | E14: 0.1
B15: =C15&"-"&D15 -> Moderado-HOTELARIAS | C15: Moderado | D15: HOTELARIAS | E15: 0.1
B16: =C16&"-"&D16 -> Agressivo-PAPEL | C16: Agressivo | D16: PAPEL | E16: 0.5
B17: =C17&"-"&D17 -> Agressivo-TIJOLO | C17: Agressivo | D17: TIJOLO | E17: 0.1
B18: =C18&"-"&D18 -> Agressivo-HÍBRIDO | C18: Agressivo | D18: HÍBRIDO | E18: 0.05
B19: =C19&"-"&D19 -> Agressivo-FOFs | C19: Agressivo | D19: FOFs | E19: 0.05
B20: =C20&"-"&D20 -> Agressivo-DESENVOLVIMENTO | C20: Agressivo | D20: DESENVOLVIMENTO | E20: 0.2
B21: =C21&"-"&D21 -> Agressivo-HOTELARIAS | C21: Agressivo | D21: HOTELARIAS | E21: 0.1
B23: Chave | C23: PERFIL | D23: TIPO DE RENDA FIXA | E23: %
B24: =C24&"-"&D24 -> Conservador-Tesouro Direto | C24: Conservador | D24: Tesouro Direto | E24: 0.35
B25: =C25&"-"&D25 -> Conservador-CDB | C25: Conservador | D25: CDB | E25: 0.3
B26: =C26&"-"&D26 -> Conservador-LCI e LCA | C26: Conservador | D26: LCI e LCA | E26: 0.25
B27: =C27&"-"&D27 -> Conservador-CRI e CRA | C27: Conservador | D27: CRI e CRA | E27: 0.05
B28: =C28&"-"&D28 -> Conservador-Dedêntures | C28: Conservador | D28: Dedêntures | E28: 0.05
B29: =C29&"-"&D29 -> Moderado-Tesouro Direto | C29: Moderado | D29: Tesouro Direto | E29: 0.25
B30: =C30&"-"&D30 -> Moderado-CDB | C30: Moderado | D30: CDB | E30: 0.25
B31: =C31&"-"&D31 -> Moderado-LCI e LCA | C31: Moderado | D31: LCI e LCA | E31: 0.2
B32: =C32&"-"&D32 -> Moderado-CRI e CRA | C32: Moderado | D32: CRI e CRA | E32: 0.15
B33: =C33&"-"&D33 -> Moderado-Dedêntures | C33: Moderado | D33: Dedêntures | E33: 0.15
B34: =C34&"-"&D34 -> Agressivo-Tesouro Direto | C34: Agressivo | D34: Tesouro Direto | E34: 0.15
B35: =C35&"-"&D35 -> Agressivo-CDB | C35: Agressivo | D35: CDB | E35: 0.2
... B38: =C38&"-"&D38 -> Agressivo-Dedêntures | C38: Agressivo | D38: Dedêntures | E38: 0.25
